pytest_valgrind-0.2.0.dist-info/top_level.txt
pytest_valgrind-0.2.0.dist-info/METADATA
pytest_valgrind-0.2.0.dist-info/RECORD
pytest_valgrind-0.2.0.dist-info/LICENSE
pytest_valgrind-0.2.0.dist-info/WHEEL
pytest_valgrind-0.2.0.dist-info/entry_points.txt
pytest_valgrind/valgrind.cpython-38-x86_64-linux-gnu.so
pytest_valgrind/__init__.py
pytest_valgrind/plugin.py
