Metadata-Version: 2.1
Name: pytest-valgrind
Version: 0.2.0
Summary: UNKNOWN
Home-page: https://github.com/fridex/pytest-valgrind
Author: Sebastian Berg
Author-email: sebastian@sipsolutions.net
Maintainer: Fridolin Pokorny
Maintainer-email: fridex.devel@gmail.com
License: UNKNOWN
Platform: UNKNOWN
Classifier: Framework :: Pytest
Classifier: License :: OSI Approved :: MIT License
Requires-Dist: pytest (>=2.9.0)
